macrorecorder/__init__.py
macrorecorder/macro_gui.py
macrorecorder/macro_recorder.py
linux_macrorecorder-1.0.2.dist-info/METADATA
linux_macrorecorder-1.0.2.dist-info/WHEEL
linux_macrorecorder-1.0.2.dist-info/entry_points.txt
linux_macrorecorder-1.0.2.dist-info/licenses/LICENSE
linux_macrorecorder-1.0.2.dist-info/RECORD
