Metadata-Version: 2.4
Name: linux_macrorecorder
Version: 1.0.2
Summary: Simple macro recorder for keystrokes on X and Wayland
Project-URL: Homepage, https://github.com/werzum/MacroRecorder
License-Expression: GPL-3.0-or-later
License-File: LICENSE
Keywords: automation,keystrokes,macro,recorder
Requires-Python: >=3.12
Requires-Dist: pycairo>=1.28.0
Requires-Dist: pygobject>=3.52.3
Requires-Dist: pynput>=1.8.1
